yacs/__init__.py
yacs/config.py
yacs/tests.py
yacs-0.1.7.dist-info/LICENSE
yacs-0.1.7.dist-info/METADATA
yacs-0.1.7.dist-info/NOTICE
yacs-0.1.7.dist-info/WHEEL
yacs-0.1.7.dist-info/top_level.txt
yacs-0.1.7.dist-info/RECORD
